{".class":"MypyFile","_fullname":"zloth_api.errors","future_import_flags":["annotations"],"is_partial_stub_package":false,"is_stub":false,"names":{".class":"SymbolTable","Any":{".class":"SymbolTableNode","cross_ref":"typing.Any","kind":"Gdef","module_hidden":true,"module_public":false},"ConflictError":{".class":"SymbolTableNode","kind":"Gdef","node":{".class":"TypeInfo","_promote":[],"abstract_attributes":[],"alt_promote":null,"bases":["zloth_api.errors.ZlothError"],"dataclass_transform_spec":null,"declared_metaclass":null,"defn":{".class":"ClassDef","fullname":"zloth_api.errors.ConflictError","name":"ConflictError","type_vars":[]},"deletable_attributes":[],"deprecated":null,"flags":[],"fullname":"zloth_api.errors.ConflictError","has_param_spec_type":false,"metaclass_type":null,"metadata":{},"module_name":"zloth_api.errors","mro":["zloth_api.errors.ConflictError","zloth_api.errors.ZlothError","builtins.Exception","builtins.BaseException","builtins.object"],"names":{".class":"SymbolTable","__init__":{".class":"SymbolTableNode","kind":"Mdef","node":{".class":"FuncDef","abstract_status":0,"arg_kinds":[0,0,5,5],"arg_names":["self","message","code","details"],"dataclass_transform_spec":null,"deprecated":null,"flags":["is_trivial_self"],"fullname":"zloth_api.errors.ConflictError.__init__","name":"__init__","original_first_arg":"self","type":{".class":"CallableType","arg_kinds":[0,0,5,5],"arg_names":["self","message","code","details"],"arg_types":["zloth_api.errors.ConflictError","builtins.str","builtins.str",{".class":"UnionType","items":[{".class":"Instance","args":["builtins.str",{".class":"AnyType","missing_import_name":null,"source_any":null,"type_of_any":2}],"extra_attrs":null,"type_ref":"builtins.dict"},{".class":"NoneType"}],"uses_pep604_syntax":true}],"fallback":"builtins.function","from_concatenate":false,"implicit":false,"imprecise_arg_kinds":false,"is_bound":false,"is_ellipsis_args":false,"name":"__init__ of ConflictError","ret_type":{".class":"NoneType"},"type_guard":null,"type_is":null,"unpack_kwargs":false,"variables":[]}}}},"self_type":{".class":"TypeVarType","default":{".class":"AnyType","missing_import_name":null,"source_any":null,"type_of_any":4},"fullname":"zloth_api.errors.ConflictError.Self","id":0,"name":"Self","namespace":"","upper_bound":"zloth_api.errors.ConflictError","values":[],"variance":0},"slots":null,"tuple_type":null,"type_vars":[],"typeddict_type":null}},"ExternalServiceError":{".class":"SymbolTableNode","kind":"Gdef","node":{".class":"TypeInfo","_promote":[],"abstract_attributes":[],"alt_promote":null,"bases":["zloth_api.errors.ZlothError"],"dataclass_transform_spec":null,"declared_metaclass":null,"defn":{".class":"ClassDef","fullname":"zloth_api.errors.ExternalServiceError","name":"ExternalServiceError","type_vars":[]},"deletable_attributes":[],"deprecated":null,"flags":[],"fullname":"zloth_api.errors.ExternalServiceError","has_param_spec_type":false,"metaclass_type":null,"metadata":{},"module_name":"zloth_api.errors","mro":["zloth_api.errors.ExternalServiceError","zloth_api.errors.ZlothError","builtins.Exception","builtins.BaseException","builtins.object"],"names":{".class":"SymbolTable","__init__":{".class":"SymbolTableNode","kind":"Mdef","node":{".class":"FuncDef","abstract_status":0,"arg_kinds":[0,1,5,5,5],"arg_names":["self","message","code","details","status_code"],"dataclass_transform_spec":null,"deprecated":null,"flags":["is_trivial_self"],"fullname":"zloth_api.errors.ExternalServiceError.__init__","name":"__init__","original_first_arg":"self","type":{".class":"CallableType","arg_kinds":[0,1,5,5,5],"arg_names":["self","message","code","details","status_code"],"arg_types":["zloth_api.errors.ExternalServiceError","builtins.str","builtins.str",{".class":"UnionType","items":[{".class":"Instance","args":["builtins.str",{".class":"AnyType","missing_import_name":null,"source_any":null,"type_of_any":2}],"extra_attrs":null,"type_ref":"builtins.dict"},{".class":"NoneType"}],"uses_pep604_syntax":true},"builtins.int"],"fallback":"builtins.function","from_concatenate":false,"implicit":false,"imprecise_arg_kinds":false,"is_bound":false,"is_ellipsis_args":false,"name":"__init__ of ExternalServiceError","ret_type":{".class":"NoneType"},"type_guard":null,"type_is":null,"unpack_kwargs":false,"variables":[]}}}},"self_type":{".class":"TypeVarType","default":{".class":"AnyType","missing_import_name":null,"source_any":null,"type_of_any":4},"fullname":"zloth_api.errors.ExternalServiceError.Self","id":0,"name":"Self","namespace":"","upper_bound":"zloth_api.errors.ExternalServiceError","values":[],"variance":0},"slots":null,"tuple_type":null,"type_vars":[],"typeddict_type":null}},"ForbiddenError":{".class":"SymbolTableNode","kind":"Gdef","node":{".class":"TypeInfo","_promote":[],"abstract_attributes":[],"alt_promote":null,"bases":["zloth_api.errors.ZlothError"],"dataclass_transform_spec":null,"declared_metaclass":null,"defn":{".class":"ClassDef","fullname":"zloth_api.errors.ForbiddenError","name":"ForbiddenError","type_vars":[]},"deletable_attributes":[],"deprecated":null,"flags":[],"fullname":"zloth_api.errors.ForbiddenError","has_param_spec_type":false,"metaclass_type":null,"metadata":{},"module_name":"zloth_api.errors","mro":["zloth_api.errors.ForbiddenError","zloth_api.errors.ZlothError","builtins.Exception","builtins.BaseException","builtins.object"],"names":{".class":"SymbolTable","__init__":{".class":"SymbolTableNode","kind":"Mdef","node":{".class":"FuncDef","abstract_status":0,"arg_kinds":[0,0,5,5],"arg_names":["self","message","code","details"],"dataclass_transform_spec":null,"deprecated":null,"flags":["is_trivial_self"],"fullname":"zloth_api.errors.ForbiddenError.__init__","name":"__init__","original_first_arg":"self","type":{".class":"CallableType","arg_kinds":[0,0,5,5],"arg_names":["self","message","code","details"],"arg_types":["zloth_api.errors.ForbiddenError","builtins.str","builtins.str",{".class":"UnionType","items":[{".class":"Instance","args":["builtins.str",{".class":"AnyType","missing_import_name":null,"source_any":null,"type_of_any":2}],"extra_attrs":null,"type_ref":"builtins.dict"},{".class":"NoneType"}],"uses_pep604_syntax":true}],"fallback":"builtins.function","from_concatenate":false,"implicit":false,"imprecise_arg_kinds":false,"is_bound":false,"is_ellipsis_args":false,"name":"__init__ of ForbiddenError","ret_type":{".class":"NoneType"},"type_guard":null,"type_is":null,"unpack_kwargs":false,"variables":[]}}}},"self_type":{".class":"TypeVarType","default":{".class":"AnyType","missing_import_name":null,"source_any":null,"type_of_any":4},"fullname":"zloth_api.errors.ForbiddenError.Self","id":0,"name":"Self","namespace":"","upper_bound":"zloth_api.errors.ForbiddenError","values":[],"variance":0},"slots":null,"tuple_type":null,"type_vars":[],"typeddict_type":null}},"NotFoundError":{".class":"SymbolTableNode","kind":"Gdef","node":{".class":"TypeInfo","_promote":[],"abstract_attributes":[],"alt_promote":null,"bases":["zloth_api.errors.ZlothError"],"dataclass_transform_spec":null,"declared_metaclass":null,"defn":{".class":"ClassDef","fullname":"zloth_api.errors.NotFoundError","name":"NotFoundError","type_vars":[]},"deletable_attributes":[],"deprecated":null,"flags":[],"fullname":"zloth_api.errors.NotFoundError","has_param_spec_type":false,"metaclass_type":null,"metadata":{},"module_name":"zloth_api.errors","mro":["zloth_api.errors.NotFoundError","zloth_api.errors.ZlothError","builtins.Exception","builtins.BaseException","builtins.object"],"names":{".class":"SymbolTable","__init__":{".class":"SymbolTableNode","kind":"Mdef","node":{".class":"FuncDef","abstract_status":0,"arg_kinds":[0,0,5,5],"arg_names":["self","message","code","details"],"dataclass_transform_spec":null,"deprecated":null,"flags":["is_trivial_self"],"fullname":"zloth_api.errors.NotFoundError.__init__","name":"__init__","original_first_arg":"self","type":{".class":"CallableType","arg_kinds":[0,0,5,5],"arg_names":["self","message","code","details"],"arg_types":["zloth_api.errors.NotFoundError","builtins.str","builtins.str",{".class":"UnionType","items":[{".class":"Instance","args":["builtins.str",{".class":"AnyType","missing_import_name":null,"source_any":null,"type_of_any":2}],"extra_attrs":null,"type_ref":"builtins.dict"},{".class":"NoneType"}],"uses_pep604_syntax":true}],"fallback":"builtins.function","from_concatenate":false,"implicit":false,"imprecise_arg_kinds":false,"is_bound":false,"is_ellipsis_args":false,"name":"__init__ of NotFoundError","ret_type":{".class":"NoneType"},"type_guard":null,"type_is":null,"unpack_kwargs":false,"variables":[]}}}},"self_type":{".class":"TypeVarType","default":{".class":"AnyType","missing_import_name":null,"source_any":null,"type_of_any":4},"fullname":"zloth_api.errors.NotFoundError.Self","id":0,"name":"Self","namespace":"","upper_bound":"zloth_api.errors.NotFoundError","values":[],"variance":0},"slots":null,"tuple_type":null,"type_vars":[],"typeddict_type":null}},"ValidationError":{".class":"SymbolTableNode","kind":"Gdef","node":{".class":"TypeInfo","_promote":[],"abstract_attributes":[],"alt_promote":null,"bases":["zloth_api.errors.ZlothError"],"dataclass_transform_spec":null,"declared_metaclass":null,"defn":{".class":"ClassDef","fullname":"zloth_api.errors.ValidationError","name":"ValidationError","type_vars":[]},"deletable_attributes":[],"deprecated":null,"flags":[],"fullname":"zloth_api.errors.ValidationError","has_param_spec_type":false,"metaclass_type":null,"metadata":{},"module_name":"zloth_api.errors","mro":["zloth_api.errors.ValidationError","zloth_api.errors.ZlothError","builtins.Exception","builtins.BaseException","builtins.object"],"names":{".class":"SymbolTable","__init__":{".class":"SymbolTableNode","kind":"Mdef","node":{".class":"FuncDef","abstract_status":0,"arg_kinds":[0,0,5,5,5],"arg_names":["self","message","code","details","status_code"],"dataclass_transform_spec":null,"deprecated":null,"flags":["is_trivial_self"],"fullname":"zloth_api.errors.ValidationError.__init__","name":"__init__","original_first_arg":"self","type":{".class":"CallableType","arg_kinds":[0,0,5,5,5],"arg_names":["self","message","code","details","status_code"],"arg_types":["zloth_api.errors.ValidationError","builtins.str","builtins.str",{".class":"UnionType","items":[{".class":"Instance","args":["builtins.str",{".class":"AnyType","missing_import_name":null,"source_any":null,"type_of_any":2}],"extra_attrs":null,"type_ref":"builtins.dict"},{".class":"NoneType"}],"uses_pep604_syntax":true},"builtins.int"],"fallback":"builtins.function","from_concatenate":false,"implicit":false,"imprecise_arg_kinds":false,"is_bound":false,"is_ellipsis_args":false,"name":"__init__ of ValidationError","ret_type":{".class":"NoneType"},"type_guard":null,"type_is":null,"unpack_kwargs":false,"variables":[]}}}},"self_type":{".class":"TypeVarType","default":{".class":"AnyType","missing_import_name":null,"source_any":null,"type_of_any":4},"fullname":"zloth_api.errors.ValidationError.Self","id":0,"name":"Self","namespace":"","upper_bound":"zloth_api.errors.ValidationError","values":[],"variance":0},"slots":null,"tuple_type":null,"type_vars":[],"typeddict_type":null}},"ZlothError":{".class":"SymbolTableNode","kind":"Gdef","node":{".class":"TypeInfo","_promote":[],"abstract_attributes":[],"alt_promote":null,"bases":["builtins.Exception"],"dataclass_transform_spec":null,"declared_metaclass":null,"defn":{".class":"ClassDef","fullname":"zloth_api.errors.ZlothError","name":"ZlothError","type_vars":[]},"deletable_attributes":[],"deprecated":null,"flags":[],"fullname":"zloth_api.errors.ZlothError","has_param_spec_type":false,"metaclass_type":null,"metadata":{"dataclass":{"attributes":[{"alias":null,"column":4,"has_default":false,"is_in_init":true,"is_init_var":false,"is_neither_frozen_nor_nonfrozen":false,"kw_only":false,"line":18,"name":"message","type":"builtins.str"},{"alias":null,"column":4,"has_default":true,"is_in_init":true,"is_init_var":false,"is_neither_frozen_nor_nonfrozen":false,"kw_only":false,"line":19,"name":"code","type":"builtins.str"},{"alias":null,"column":4,"has_default":true,"is_in_init":true,"is_init_var":false,"is_neither_frozen_nor_nonfrozen":false,"kw_only":false,"line":20,"name":"status_code","type":"builtins.int"},{"alias":null,"column":4,"has_default":true,"is_in_init":true,"is_init_var":false,"is_neither_frozen_nor_nonfrozen":false,"kw_only":false,"line":21,"name":"details","type":{".class":"UnionType","items":[{".class":"Instance","args":["builtins.str",{".class":"AnyType","missing_import_name":null,"source_any":null,"type_of_any":2}],"extra_attrs":null,"type_ref":"builtins.dict"},{".class":"NoneType"}],"uses_pep604_syntax":true}}],"frozen":true},"dataclass_tag":{}},"module_name":"zloth_api.errors","mro":["zloth_api.errors.ZlothError","builtins.Exception","builtins.BaseException","builtins.object"],"names":{".class":"SymbolTable","__dataclass_fields__":{".class":"SymbolTableNode","kind":"Mdef","node":{".class":"Var","flags":["is_classvar","is_ready"],"fullname":"zloth_api.errors.ZlothError.__dataclass_fields__","name":"__dataclass_fields__","setter_type":null,"type":{".class":"Instance","args":["builtins.str",{".class":"Instance","args":[{".class":"AnyType","missing_import_name":null,"source_any":null,"type_of_any":2}],"extra_attrs":null,"type_ref":"dataclasses.Field"}],"extra_attrs":null,"type_ref":"builtins.dict"}},"plugin_generated":true},"__init__":{".class":"SymbolTableNode","kind":"Mdef","node":{".class":"FuncDef","abstract_status":0,"arg_kinds":[0,0,1,1,1],"arg_names":["self","message","code","status_code","details"],"dataclass_transform_spec":null,"deprecated":null,"flags":[],"fullname":"zloth_api.errors.ZlothError.__init__","name":"__init__","original_first_arg":"self","type":{".class":"CallableType","arg_kinds":[0,0,1,1,1],"arg_names":["self","message","code","status_code","details"],"arg_types":["zloth_api.errors.ZlothError","builtins.str","builtins.str","builtins.int",{".class":"UnionType","items":[{".class":"Instance","args":["builtins.str",{".class":"AnyType","missing_import_name":null,"source_any":null,"type_of_any":2}],"extra_attrs":null,"type_ref":"builtins.dict"},{".class":"NoneType"}],"uses_pep604_syntax":false}],"fallback":"builtins.function","from_concatenate":false,"implicit":false,"imprecise_arg_kinds":false,"is_bound":false,"is_ellipsis_args":false,"name":"__init__ of ZlothError","ret_type":{".class":"NoneType"},"type_guard":null,"type_is":null,"unpack_kwargs":false,"variables":[]}},"plugin_generated":true},"__match_args__":{".class":"SymbolTableNode","kind":"Mdef","node":{".class":"Var","flags":["is_ready","allow_incompatible_override"],"fullname":"zloth_api.errors.ZlothError.__match_args__","name":"__match_args__","setter_type":null,"type":{".class":"TupleType","implicit":false,"items":[{".class":"LiteralType","fallback":"builtins.str","value":"message"},{".class":"LiteralType","fallback":"builtins.str","value":"code"},{".class":"LiteralType","fallback":"builtins.str","value":"status_code"},{".class":"LiteralType","fallback":"builtins.str","value":"details"}],"partial_fallback":{".class":"Instance","args":[{".class":"AnyType","missing_import_name":null,"source_any":null,"type_of_any":6}],"extra_attrs":null,"type_ref":"builtins.tuple"}}},"plugin_generated":true},"__mypy-replace":{".class":"SymbolTableNode","kind":"Mdef","node":{".class":"Decorator","func":{".class":"FuncDef","abstract_status":0,"arg_kinds":[5,5,5,5],"arg_names":["message","code","status_code","details"],"dataclass_transform_spec":null,"deprecated":null,"flags":["is_static","is_decorated"],"fullname":"zloth_api.errors.ZlothError.__mypy-replace","name":"__mypy-replace","original_first_arg":"message","type":{".class":"CallableType","arg_kinds":[5,5,5,5],"arg_names":["message","code","status_code","details"],"arg_types":["builtins.str","builtins.str","builtins.int",{".class":"UnionType","items":[{".class":"Instance","args":["builtins.str",{".class":"AnyType","missing_import_name":null,"source_any":null,"type_of_any":2}],"extra_attrs":null,"type_ref":"builtins.dict"},{".class":"NoneType"}],"uses_pep604_syntax":false}],"fallback":"builtins.function","from_concatenate":false,"implicit":false,"imprecise_arg_kinds":false,"is_bound":false,"is_ellipsis_args":false,"name":"__mypy-replace of ZlothError","ret_type":{".class":"NoneType"},"type_guard":null,"type_is":null,"unpack_kwargs":false,"variables":[]}},"is_overload":false,"var":{".class":"Var","flags":["is_staticmethod","is_ready"],"fullname":"zloth_api.errors.ZlothError.__mypy-replace","name":"__mypy-replace","setter_type":null,"type":{".class":"CallableType","arg_kinds":[5,5,5,5],"arg_names":["message","code","status_code","details"],"arg_types":["builtins.str","builtins.str","builtins.int",{".class":"UnionType","items":[{".class":"Instance","args":["builtins.str",{".class":"AnyType","missing_import_name":null,"source_any":null,"type_of_any":2}],"extra_attrs":null,"type_ref":"builtins.dict"},{".class":"NoneType"}],"uses_pep604_syntax":false}],"fallback":"builtins.function","from_concatenate":false,"implicit":false,"imprecise_arg_kinds":false,"is_bound":false,"is_ellipsis_args":false,"name":"__mypy-replace of ZlothError","ret_type":{".class":"NoneType"},"type_guard":null,"type_is":null,"unpack_kwargs":false,"variables":[]}}},"plugin_generated":true},"__replace__":{".class":"SymbolTableNode","kind":"Mdef","node":{".class":"FuncDef","abstract_status":0,"arg_kinds":[0,5,5,5,5],"arg_names":["self","message","code","status_code","details"],"dataclass_transform_spec":null,"deprecated":null,"flags":[],"fullname":"zloth_api.errors.ZlothError.__replace__","name":"__replace__","original_first_arg":"self","type":{".class":"CallableType","arg_kinds":[0,5,5,5,5],"arg_names":["self","message","code","status_code","details"],"arg_types":["zloth_api.errors.ZlothError","builtins.str","builtins.str","builtins.int",{".class":"UnionType","items":[{".class":"Instance","args":["builtins.str",{".class":"AnyType","missing_import_name":null,"source_any":null,"type_of_any":2}],"extra_attrs":null,"type_ref":"builtins.dict"},{".class":"NoneType"}],"uses_pep604_syntax":false}],"fallback":"builtins.function","from_concatenate":false,"implicit":false,"imprecise_arg_kinds":false,"is_bound":false,"is_ellipsis_args":false,"name":"__replace__ of ZlothError","ret_type":"zloth_api.errors.ZlothError","type_guard":null,"type_is":null,"unpack_kwargs":false,"variables":[]}},"plugin_generated":true},"__str__":{".class":"SymbolTableNode","kind":"Mdef","node":{".class":"FuncDef","abstract_status":0,"arg_kinds":[0],"arg_names":[null],"dataclass_transform_spec":null,"deprecated":null,"flags":["is_trivial_self"],"fullname":"zloth_api.errors.ZlothError.__str__","name":"__str__","original_first_arg":"self","type":{".class":"CallableType","arg_kinds":[0],"arg_names":[null],"arg_types":["zloth_api.errors.ZlothError"],"fallback":"builtins.function","from_concatenate":false,"implicit":false,"imprecise_arg_kinds":false,"is_bound":false,"is_ellipsis_args":false,"name":"__str__ of ZlothError","ret_type":"builtins.str","type_guard":null,"type_is":null,"unpack_kwargs":false,"variables":[]}}},"code":{".class":"SymbolTableNode","kind":"Mdef","node":{".class":"Var","flags":["is_initialized_in_class","is_property","is_ready","has_explicit_value"],"fullname":"zloth_api.errors.ZlothError.code","name":"code","setter_type":null,"type":"builtins.str"}},"details":{".class":"SymbolTableNode","kind":"Mdef","node":{".class":"Var","flags":["is_initialized_in_class","is_property","is_ready","has_explicit_value"],"fullname":"zloth_api.errors.ZlothError.details","name":"details","setter_type":null,"type":{".class":"UnionType","items":[{".class":"Instance","args":["builtins.str",{".class":"AnyType","missing_import_name":null,"source_any":null,"type_of_any":2}],"extra_attrs":null,"type_ref":"builtins.dict"},{".class":"NoneType"}],"uses_pep604_syntax":true}}},"message":{".class":"SymbolTableNode","implicit":true,"kind":"Mdef","node":{".class":"Var","flags":["is_initialized_in_class","is_property","is_ready"],"fullname":"zloth_api.errors.ZlothError.message","name":"message","setter_type":null,"type":"builtins.str"}},"status_code":{".class":"SymbolTableNode","kind":"Mdef","node":{".class":"Var","flags":["is_initialized_in_class","is_property","is_ready","has_explicit_value"],"fullname":"zloth_api.errors.ZlothError.status_code","name":"status_code","setter_type":null,"type":"builtins.int"}}},"self_type":{".class":"TypeVarType","default":{".class":"AnyType","missing_import_name":null,"source_any":null,"type_of_any":4},"fullname":"zloth_api.errors.ZlothError.Self","id":0,"name":"Self","namespace":"","upper_bound":"zloth_api.errors.ZlothError","values":[],"variance":0},"slots":null,"tuple_type":null,"type_vars":[],"typeddict_type":null}},"__annotations__":{".class":"SymbolTableNode","kind":"Gdef","node":{".class":"Var","flags":["is_ready"],"fullname":"zloth_api.errors.__annotations__","name":"__annotations__","setter_type":null,"type":{".class":"Instance","args":["builtins.str",{".class":"AnyType","missing_import_name":null,"source_any":null,"type_of_any":6}],"extra_attrs":null,"type_ref":"builtins.dict"}}},"__doc__":{".class":"SymbolTableNode","kind":"Gdef","node":{".class":"Var","flags":["is_ready"],"fullname":"zloth_api.errors.__doc__","name":"__doc__","setter_type":null,"type":"builtins.str"}},"__file__":{".class":"SymbolTableNode","kind":"Gdef","node":{".class":"Var","flags":["is_ready"],"fullname":"zloth_api.errors.__file__","name":"__file__","setter_type":null,"type":"builtins.str"}},"__name__":{".class":"SymbolTableNode","kind":"Gdef","node":{".class":"Var","flags":["is_ready"],"fullname":"zloth_api.errors.__name__","name":"__name__","setter_type":null,"type":"builtins.str"}},"__package__":{".class":"SymbolTableNode","kind":"Gdef","node":{".class":"Var","flags":["is_ready"],"fullname":"zloth_api.errors.__package__","name":"__package__","setter_type":null,"type":"builtins.str"}},"__spec__":{".class":"SymbolTableNode","kind":"Gdef","node":{".class":"Var","flags":["is_ready"],"fullname":"zloth_api.errors.__spec__","name":"__spec__","setter_type":null,"type":"_frozen_importlib.ModuleSpec"}},"annotations":{".class":"SymbolTableNode","cross_ref":"__future__.annotations","kind":"Gdef","module_hidden":true,"module_public":false},"dataclass":{".class":"SymbolTableNode","cross_ref":"dataclasses.dataclass","kind":"Gdef","module_hidden":true,"module_public":false}},"path":"src/zloth_api/errors.py"}